mangoml/__init__.py
mangoml/data/__init__.py
mangoml/data/data.py
mangoml/data/data_formatter.py
mangoml/data/result.py
mangoml/data/text_formatter.py
mangoml/data/engines/__init__.py
mangoml/data/engines/engine_factory.py
mangoml/data/engines/pandas_engine.py
mangoml/model/__init__.py
mangoml/model/base_model.py
mangoml/model/model_pool.py
mangoml/model/pipeline_model.py
mangoml/model/ensembles/__init__.py
mangoml/model/ensembles/base_two_level_ensembler.py
mangoml/model/ensembles/ensembler_factory.py
mangoml/model/ensembles/two_level_ensemblers.py
mangoml/model/ensembles/voting_ensembler.py
mangoml/model/feature_editor/__init__.py
mangoml/model/feature_editor/feature_editor.py
mangoml/model/feature_editor/feature_eraser.py
mangoml/model/feature_editor/feature_selector.py
mangoml/model/model_calibrators/__init__.py
mangoml/model/model_calibrators/model_calibrator_factory.py
mangoml/model/models/__init__.py
mangoml/model/models/model_factory.py
mangoml/model/models/regressors/__init__.py
mangoml/model/models/regressors/prophet_wrapper.py
mangoml/model/preprocessors/__init__.py
mangoml/model/preprocessors/preprocessor_factory.py
mangoml/model/preprocessors/transformers/__init__.py
mangoml/model/preprocessors/transformers/mean_word_length_transformer.py
mangoml/model/preprocessors/transformers/model_wrapper_transformer.py
mangoml/model/preprocessors/transformers/sentence_length_transformer.py
mangoml/model/preprocessors/transformers/stopword_count_transformer.py
mangoml/model/preprocessors/transformers/word_count_transformer.py
mangoml/model/scores/__init__.py
mangoml/model/scores/score_method_factory.py
mangoml/model/scores/scorer.py
mangoml/model/splitters/__init__.py
mangoml/model/splitters/datetime_splitter.py
mangoml/model/splitters/fixed_size_splitter.py
mangoml/model/splitters/splitter_factory.py
mangoml/model/splitters/splitter_wrapper.py
mangoml-0.0.2.dist-info/METADATA
mangoml-0.0.2.dist-info/RECORD
mangoml-0.0.2.dist-info/WHEEL
mangoml-0.0.2.dist-info/top_level.txt
