Metadata-Version: 2.1
Name: mangoml
Version: 0.0.2
Summary: Simple Machine Learning library
Home-page: https://bitbucket.org/gustavosantos/bam_kaggle
Author: Gustavo Santos
Author-email: gustavohas@outlook.com
License: UNKNOWN
Platform: UNKNOWN
Classifier: Programming Language :: Python :: 2
Classifier: License :: OSI Approved :: BSD License
Classifier: Operating System :: OS Independent
Requires-Dist: sklearn
Requires-Dist: bs4
Requires-Dist: nltk (>=3.2.5)
Requires-Dist: fbprophet (>=0.2.1)
Requires-Dist: pystan
Requires-Dist: catboost (>=0.6.2)
Requires-Dist: lightgbm (>=2.1.0)
Requires-Dist: xgboost
Requires-Dist: pandas (>=0.21)
Requires-Dist: matplotlib (>=2.1.1)
Requires-Dist: scipy (>=1.0.0)
Requires-Dist: numpy (>=1.13)
Requires-Dist: Cython
